{
  "features": [
    {
      "type": "Feature",
      "properties": {
        "Label": "Casa de Tablas"
      },
      "geometry": {
        "coordinates": [
          -78.401053,
          -0.360334
        ],
        "type": "Point"
      },
      "id": "44e3a3d469af93c633bd218ebaec8da5"
    },
    {
      "type": "Feature",
      "properties": {
        "Label": "Parada Capelo 2"
      },
      "geometry": {
        "coordinates": [
          -78.396106,
          -0.364598
        ],
        "type": "Point"
      },
      "id": "66d59801f65fdbeacc0a483d02189444"
    },
    {
      "type": "Feature",
      "properties": {
        "Label": "Fla. Araki"
      },
      "geometry": {
        "coordinates": [
          -78.403748,
          -0.353376
        ],
        "type": "Point"
      },
      "id": "6ea5c4429125564c63d68d0aea1617ab"
    },
    {
      "type": "Feature",
      "properties": {
        "Label": "Santa Teresa C"
      },
      "geometry": {
        "coordinates": [
          [
            [
              -78.405706,
              -0.342795
            ],
            [
              -78.403483,
              -0.344865
            ],
            [
              -78.402635,
              -0.346275
            ],
            [
              -78.401897,
              -0.349171
            ],
            [
              -78.400703,
              -0.350207
            ],
            [
              -78.400114,
              -0.351462
            ],
            [
              -78.401565,
              -0.359634
            ],
            [
              -78.401028,
              -0.359913
            ],
            [
              -78.398193,
              -0.361516
            ],
            [
              -78.396485,
              -0.36263
            ],
            [
              -78.396114,
              -0.364215
            ],
            [
              -78.395852,
              -0.365028
            ],
            [
              -78.399394,
              -0.369507
            ],
            [
              -78.401756,
              -0.369205
            ],
            [
              -78.402166,
              -0.368563
            ],
            [
              -78.401807,
              -0.367426
            ],
            [
              -78.401583,
              -0.365647
            ],
            [
              -78.401961,
              -0.365389
            ],
            [
              -78.402768,
              -0.366195
            ],
            [
              -78.403686,
              -0.366176
            ],
            [
              -78.404367,
              -0.365258
            ],
            [
              -78.405061,
              -0.364134
            ],
            [
              -78.404874,
              -0.362404
            ],
            [
              -78.405788,
              -0.361913
            ],
            [
              -78.407418,
              -0.363017
            ],
            [
              -78.407537,
              -0.362033
            ],
            [
              -78.407184,
              -0.361514
            ],
            [
              -78.407161,
              -0.359345
            ],
            [
              -78.407583,
              -0.358801
            ],
            [
              -78.408729,
              -0.358998
            ],
            [
              -78.40916,
              -0.358478
            ],
            [
              -78.409233,
              -0.35742
            ],
            [
              -78.409857,
              -0.356526
            ],
            [
              -78.407839,
              -0.354987
            ],
            [
              -78.407802,
              -0.353008
            ],
            [
              -78.408673,
              -0.353387
            ],
            [
              -78.409544,
              -0.353215
            ],
            [
              -78.410075,
              -0.353532
            ],
            [
              -78.412349,
              -0.352791
            ],
            [
              -78.412056,
              -0.351609
            ],
            [
              -78.411524,
              -0.351046
            ],
            [
              -78.411762,
              -0.350042
            ],
            [
              -78.412349,
              -0.349355
            ],
            [
              -78.413522,
              -0.349259
            ],
            [
              -78.414696,
              -0.348668
            ],
            [
              -78.405706,
              -0.342795
            ]
          ]
        ],
        "type": "Polygon"
      },
      "id": "c2b568ff373a8ea0292614b836221a85"
    }
  ],
  "type": "FeatureCollection"
}
